LICENSE
README.md
clearsoda/__init__.py
clearsoda/code.py
clearsoda/codeprimitives.py
clearsoda/helpers.py
clearsoda/looks.py
clearsoda/motion.py
clearsoda/operator.py
clearsoda/project.py
clearsoda/py.typed
clearsoda/sensing.py
clearsoda/sound.py
clearsoda-0.0.2.dist-info/LICENSE
clearsoda-0.0.2.dist-info/WHEEL
clearsoda-0.0.2.dist-info/METADATA
clearsoda-0.0.2.dist-info/RECORD
